MANIFEST.in
README.md
benchmark.py
fabricate.py
setup.cfg
setup.py
fabricate.egg-info/PKG-INFO
fabricate.egg-info/SOURCES.txt
fabricate.egg-info/dependency_links.txt
fabricate.egg-info/requires.txt
fabricate.egg-info/top_level.txt
test/test_fabricate.py