Metadata-Version: 1.1
Name: fabricate
Version: 1.29.0
Summary: The better build tool. Finds dependencies automatically for any language.
Home-page: https://github.com/SimonAlfie/fabricate/
Author: Chris Coetzee
Author-email: chriscz93@gmail.com
License: New BSD License
Keywords: fabricate make python build
Platform: Operating System :: Microsoft :: Windows
Platform: Operating System :: MacOS
Platform: Operating System :: POSIX :: Linux
Classifier: License :: OSI Approved :: BSD License
Classifier: Programming Language :: Python
Classifier: Topic :: Software Development :: Build Tools
Classifier: Programming Language :: Python :: 2.6
Classifier: Programming Language :: Python :: 2.7
Classifier: Programming Language :: Python :: 3.2
Classifier: Programming Language :: Python :: 3.3
Classifier: Programming Language :: Python :: 3.4
Classifier: Programming Language :: Python :: 3.5
Classifier: Programming Language :: Python :: 3.6
